[
  {
    "from": {
      "name": "David Fowler",
      "Company": "Accenture",
      "li_profile": "",
      "title": "Programme Lead",
      "avatar": ""
    },
    "content": "Alex worked for me for approx an 8 month period, acting as our lead developer for a very significant digital transformation (one of the big four UK utility firms).\nWe found Alex to be extremely professional and dependable, often going the extra mile (working evenings and weekends) to get the job done.\nAlex's deep experience in this area is evident both in the quality of his work, and his clear articulation of problems/challenges alongside workable solutions.\nI would happily recommend Alex and would certainly use again."
  }
]